{
    "last_updated": "2026-07-21 17:01:22",
    "stocks": [
        {
            "Symbol": "PCJEWELLER",
            "Price (\u20b9)": 10.08,
            "50 DMA": 9.12,
            "100 DMA": 9.07,
            "200 DMA": 9.96,
            "Dist from 200 DMA": "1.21%",
            "CAR Signal": "AVOID (CAR Falling)"
        },
        {
            "Symbol": "IDEA",
            "Price (\u20b9)": 13.49,
            "50 DMA": 14.11,
            "100 DMA": 11.94,
            "200 DMA": 11.21,
            "Dist from 200 DMA": "20.37%",
            "CAR Signal": "AVOID (CAR Falling)"
        },
        {
            "Symbol": "JPPOWER",
            "Price (\u20b9)": 17.75,
            "50 DMA": 18.31,
            "100 DMA": 17.48,
            "200 DMA": 17.38,
            "Dist from 200 DMA": "2.13%",
            "CAR Signal": "AVOID (CAR Falling)"
        },
        {
            "Symbol": "JINDWORLD",
            "Price (\u20b9)": 37.64,
            "50 DMA": 29.65,
            "100 DMA": 26.71,
            "200 DMA": 28.89,
            "Dist from 200 DMA": "30.28%",
            "CAR Signal": "BUY (CAR Rising)"
        },
        {
            "Symbol": "KARURVYSYA",
            "Price (\u20b9)": 340.3,
            "50 DMA": 294.09,
            "100 DMA": 293.18,
            "200 DMA": 277.9,
            "Dist from 200 DMA": "22.46%",
            "CAR Signal": "Short History"
        },
        {
            "Symbol": "YESBANK",
            "Price (\u20b9)": 23.14,
            "50 DMA": 23.45,
            "100 DMA": 21.55,
            "200 DMA": 21.86,
            "Dist from 200 DMA": "5.84%",
            "CAR Signal": "AVOID (CAR Falling)"
        },
        {
            "Symbol": "BEPL",
            "Price (\u20b9)": 123.44,
            "50 DMA": 99.42,
            "100 DMA": 94.07,
            "200 DMA": 91.44,
            "Dist from 200 DMA": "35.0%",
            "CAR Signal": "Short History"
        },
        {
            "Symbol": "NHPC",
            "Price (\u20b9)": 80.31,
            "50 DMA": 77.85,
            "100 DMA": 77.99,
            "200 DMA": 78.48,
            "Dist from 200 DMA": "2.34%",
            "CAR Signal": "BUY (CAR Rising)"
        },
        {
            "Symbol": "HDFCBANK",
            "Price (\u20b9)": 761.45,
            "50 DMA": 773.39,
            "100 DMA": 782.23,
            "200 DMA": 868.55,
            "Dist from 200 DMA": "-12.33%",
            "CAR Signal": "AVOID (CAR Falling)"
        },
        {
            "Symbol": "TATSILV",
            "Price (\u20b9)": 21.56,
            "50 DMA": 23.42,
            "100 DMA": 23.61,
            "200 DMA": 21.64,
            "Dist from 200 DMA": "-0.38%",
            "CAR Signal": "AVOID (CAR Falling)"
        },
        {
            "Symbol": "BECTORFOOD",
            "Price (\u20b9)": 211.3,
            "50 DMA": 180.03,
            "100 DMA": 186.46,
            "200 DMA": 215.16,
            "Dist from 200 DMA": "-1.8%",
            "CAR Signal": "AVOID (CAR Falling)"
        },
        {
            "Symbol": "GTLINFRA",
            "Price (\u20b9)": 1.25,
            "50 DMA": 1.39,
            "100 DMA": 1.27,
            "200 DMA": 1.27,
            "Dist from 200 DMA": "-1.89%",
            "CAR Signal": "AVOID (CAR Falling)"
        },
        {
            "Symbol": "UNIONBANK",
            "Price (\u20b9)": 176.11,
            "50 DMA": 164.32,
            "100 DMA": 169.08,
            "200 DMA": 161.83,
            "Dist from 200 DMA": "8.83%",
            "CAR Signal": "BUY (CAR Rising)"
        },
        {
            "Symbol": "SOUTHBANK",
            "Price (\u20b9)": 47.28,
            "50 DMA": 44.18,
            "100 DMA": 41.44,
            "200 DMA": 40.21,
            "Dist from 200 DMA": "17.58%",
            "CAR Signal": "AVOID (CAR Falling)"
        },
        {
            "Symbol": "OLAELEC",
            "Price (\u20b9)": 38.72,
            "50 DMA": 41.12,
            "100 DMA": 35.81,
            "200 DMA": 37.87,
            "Dist from 200 DMA": "2.24%",
            "CAR Signal": "AVOID (CAR Falling)"
        },
        {
            "Symbol": "SUZLON",
            "Price (\u20b9)": 53.17,
            "50 DMA": 55.21,
            "100 DMA": 50.95,
            "200 DMA": 51.54,
            "Dist from 200 DMA": "3.17%",
            "CAR Signal": "AVOID (CAR Falling)"
        },
        {
            "Symbol": "KALYANKJIL",
            "Price (\u20b9)": 577.0,
            "50 DMA": 393.85,
            "100 DMA": 399.05,
            "200 DMA": 433.82,
            "Dist from 200 DMA": "33.0%",
            "CAR Signal": "BUY (CAR Rising)"
        },
        {
            "Symbol": "PNB",
            "Price (\u20b9)": 112.08,
            "50 DMA": 104.65,
            "100 DMA": 106.93,
            "200 DMA": 112.63,
            "Dist from 200 DMA": "-0.49%",
            "CAR Signal": "AVOID (CAR Falling)"
        },
        {
            "Symbol": "STALLION",
            "Price (\u20b9)": 245.32,
            "50 DMA": 184.61,
            "100 DMA": 158.58,
            "200 DMA": 191.64,
            "Dist from 200 DMA": "28.01%",
            "CAR Signal": "BUY (CAR Rising)"
        },
        {
            "Symbol": "CUPID",
            "Price (\u20b9)": 211.25,
            "50 DMA": 165.27,
            "100 DMA": 131.03,
            "200 DMA": 101.51,
            "Dist from 200 DMA": "108.11%",
            "CAR Signal": "AVOID (CAR Falling)"
        },
        {
            "Symbol": "CANBK",
            "Price (\u20b9)": 127.52,
            "50 DMA": 127.79,
            "100 DMA": 130.97,
            "200 DMA": 135.51,
            "Dist from 200 DMA": "-5.9%",
            "CAR Signal": "AVOID (CAR Falling)"
        },
        {
            "Symbol": "MOTISONS",
            "Price (\u20b9)": 13.69,
            "50 DMA": 13.19,
            "100 DMA": 13.33,
            "200 DMA": 14.41,
            "Dist from 200 DMA": "-5.01%",
            "CAR Signal": "AVOID (CAR Falling)"
        },
        {
            "Symbol": "BLUESTONE",
            "Price (\u20b9)": 728.65,
            "50 DMA": 532.76,
            "100 DMA": 512.94,
            "200 DMA": 529.44,
            "Dist from 200 DMA": "37.63%",
            "CAR Signal": "BUY (CAR Rising)"
        },
        {
            "Symbol": "ETERNAL",
            "Price (\u20b9)": 286.6,
            "50 DMA": 261.34,
            "100 DMA": 251.62,
            "200 DMA": 275.45,
            "Dist from 200 DMA": "4.05%",
            "CAR Signal": "BUY (CAR Rising)"
        },
        {
            "Symbol": "TATASTEEL",
            "Price (\u20b9)": 187.24,
            "50 DMA": 197.27,
            "100 DMA": 198.46,
            "200 DMA": 187.78,
            "Dist from 200 DMA": "-0.29%",
            "CAR Signal": "AVOID (CAR Falling)"
        },
        {
            "Symbol": "HSCL",
            "Price (\u20b9)": 800.9,
            "50 DMA": 653.37,
            "100 DMA": 576.67,
            "200 DMA": 520.05,
            "Dist from 200 DMA": "54.0%",
            "CAR Signal": "Short History"
        },
        {
            "Symbol": "DIACABS",
            "Price (\u20b9)": 269.07,
            "50 DMA": 207.22,
            "100 DMA": 175.33,
            "200 DMA": 157.71,
            "Dist from 200 DMA": "70.61%",
            "CAR Signal": "Short History"
        },
        {
            "Symbol": "JAYNECOIND",
            "Price (\u20b9)": 88.13,
            "50 DMA": 93.75,
            "100 DMA": 90.49,
            "200 DMA": 83.46,
            "Dist from 200 DMA": "5.6%",
            "CAR Signal": "AVOID (CAR Falling)"
        },
        {
            "Symbol": "M&MFIN",
            "Price (\u20b9)": 349.85,
            "50 DMA": 304.48,
            "100 DMA": 308.54,
            "200 DMA": 323.39,
            "Dist from 200 DMA": "8.18%",
            "CAR Signal": "BUY (CAR Rising)"
        },
        {
            "Symbol": "SAGILITY",
            "Price (\u20b9)": 41.84,
            "50 DMA": 40.86,
            "100 DMA": 40.9,
            "200 DMA": 45.16,
            "Dist from 200 DMA": "-7.35%",
            "CAR Signal": "AVOID (CAR Falling)"
        },
        {
            "Symbol": "HFCL",
            "Price (\u20b9)": 217.97,
            "50 DMA": 190.22,
            "100 DMA": 139.65,
            "200 DMA": 104.98,
            "Dist from 200 DMA": "107.63%",
            "CAR Signal": "AVOID (CAR Falling)"
        },
        {
            "Symbol": "FCL",
            "Price (\u20b9)": 40.05,
            "50 DMA": 38.29,
            "100 DMA": 30.59,
            "200 DMA": 27.49,
            "Dist from 200 DMA": "45.69%",
            "CAR Signal": "AVOID (CAR Falling)"
        },
        {
            "Symbol": "IOB",
            "Price (\u20b9)": 35.25,
            "50 DMA": 33.92,
            "100 DMA": 34.01,
            "200 DMA": 35.64,
            "Dist from 200 DMA": "-1.09%",
            "CAR Signal": "AVOID (CAR Falling)"
        },
        {
            "Symbol": "ADANIPOWER",
            "Price (\u20b9)": 220.37,
            "50 DMA": 225.5,
            "100 DMA": 201.29,
            "200 DMA": 174.59,
            "Dist from 200 DMA": "26.22%",
            "CAR Signal": "AVOID (CAR Falling)"
        },
        {
            "Symbol": "ICICIBANK",
            "Price (\u20b9)": 1463.1,
            "50 DMA": 1330.75,
            "100 DMA": 1313.2,
            "200 DMA": 1345.85,
            "Dist from 200 DMA": "8.71%",
            "CAR Signal": "BUY (CAR Rising)"
        },
        {
            "Symbol": "IDFCFIRSTB",
            "Price (\u20b9)": 81.66,
            "50 DMA": 75.43,
            "100 DMA": 71.03,
            "200 DMA": 75.9,
            "Dist from 200 DMA": "7.59%",
            "CAR Signal": "BUY (CAR Rising)"
        },
        {
            "Symbol": "GMRAIRPORT",
            "Price (\u20b9)": 111.48,
            "50 DMA": 105.07,
            "100 DMA": 99.86,
            "200 DMA": 99.0,
            "Dist from 200 DMA": "12.61%",
            "CAR Signal": "AVOID (CAR Falling)"
        },
        {
            "Symbol": "JIOFIN",
            "Price (\u20b9)": 240.03,
            "50 DMA": 237.64,
            "100 DMA": 239.63,
            "200 DMA": 265.5,
            "Dist from 200 DMA": "-9.59%",
            "CAR Signal": "AVOID (CAR Falling)"
        },
        {
            "Symbol": "KOTAKBANK",
            "Price (\u20b9)": 385.95,
            "50 DMA": 388.37,
            "100 DMA": 383.47,
            "200 DMA": 404.28,
            "Dist from 200 DMA": "-4.53%",
            "CAR Signal": "AVOID (CAR Falling)"
        },
        {
            "Symbol": "MRPL",
            "Price (\u20b9)": 176.31,
            "50 DMA": 155.2,
            "100 DMA": 167.68,
            "200 DMA": 162.56,
            "Dist from 200 DMA": "8.46%",
            "CAR Signal": "BUY (CAR Rising)"
        },
        {
            "Symbol": "AXISBANK",
            "Price (\u20b9)": 1258.2,
            "50 DMA": 1309.8,
            "100 DMA": 1298.83,
            "200 DMA": 1283.76,
            "Dist from 200 DMA": "-1.99%",
            "CAR Signal": "AVOID (CAR Falling)"
        },
        {
            "Symbol": "NMDC",
            "Price (\u20b9)": 83.93,
            "50 DMA": 87.99,
            "100 DMA": 85.75,
            "200 DMA": 81.04,
            "Dist from 200 DMA": "3.57%",
            "CAR Signal": "AVOID (CAR Falling)"
        },
        {
            "Symbol": "HCC",
            "Price (\u20b9)": 22.66,
            "50 DMA": 23.75,
            "100 DMA": 20.91,
            "200 DMA": 21.54,
            "Dist from 200 DMA": "5.21%",
            "CAR Signal": "BUY (CAR Rising)"
        },
        {
            "Symbol": "MOL",
            "Price (\u20b9)": 54.4,
            "50 DMA": 49.04,
            "100 DMA": 48.94,
            "200 DMA": 57.81,
            "Dist from 200 DMA": "-5.9%",
            "CAR Signal": "AVOID (CAR Falling)"
        },
        {
            "Symbol": "BANKBARODA",
            "Price (\u20b9)": 247.7,
            "50 DMA": 261.98,
            "100 DMA": 265.51,
            "200 DMA": 272.5,
            "Dist from 200 DMA": "-9.1%",
            "CAR Signal": "AVOID (CAR Falling)"
        },
        {
            "Symbol": "ZEEL",
            "Price (\u20b9)": 107.58,
            "50 DMA": 101.34,
            "100 DMA": 91.96,
            "200 DMA": 93.9,
            "Dist from 200 DMA": "14.57%",
            "CAR Signal": "BUY (CAR Rising)"
        },
        {
            "Symbol": "RELIANCE",
            "Price (\u20b9)": 1303.7,
            "50 DMA": 1312.83,
            "100 DMA": 1344.45,
            "200 DMA": 1408.01,
            "Dist from 200 DMA": "-7.41%",
            "CAR Signal": "AVOID (CAR Falling)"
        },
        {
            "Symbol": "PAISALO",
            "Price (\u20b9)": 72.18,
            "50 DMA": 59.74,
            "100 DMA": 49.74,
            "200 DMA": 42.86,
            "Dist from 200 DMA": "68.41%",
            "CAR Signal": "Short History"
        },
        {
            "Symbol": "BANKINDIA",
            "Price (\u20b9)": 147.1,
            "50 DMA": 141.86,
            "100 DMA": 143.22,
            "200 DMA": 142.84,
            "Dist from 200 DMA": "2.98%",
            "CAR Signal": "BUY (CAR Rising)"
        },
        {
            "Symbol": "SDBL",
            "Price (\u20b9)": 72.44,
            "50 DMA": 75.56,
            "100 DMA": 77.9,
            "200 DMA": 93.53,
            "Dist from 200 DMA": "-22.55%",
            "CAR Signal": "AVOID (CAR Falling)"
        },
        {
            "Symbol": "BANDHANBNK",
            "Price (\u20b9)": 208.83,
            "50 DMA": 204.42,
            "100 DMA": 189.83,
            "200 DMA": 172.34,
            "Dist from 200 DMA": "21.17%",
            "CAR Signal": "BUY (CAR Rising)"
        },
        {
            "Symbol": "ONGC",
            "Price (\u20b9)": 249.89,
            "50 DMA": 258.58,
            "100 DMA": 269.78,
            "200 DMA": 255.92,
            "Dist from 200 DMA": "-2.36%",
            "CAR Signal": "AVOID (CAR Falling)"
        },
        {
            "Symbol": "IOC",
            "Price (\u20b9)": 143.3,
            "50 DMA": 140.53,
            "100 DMA": 144.68,
            "200 DMA": 152.09,
            "Dist from 200 DMA": "-5.78%",
            "CAR Signal": "AVOID (CAR Falling)"
        },
        {
            "Symbol": "ASHOKLEY",
            "Price (\u20b9)": 153.94,
            "50 DMA": 154.41,
            "100 DMA": 162.79,
            "200 DMA": 163.91,
            "Dist from 200 DMA": "-6.08%",
            "CAR Signal": "AVOID (CAR Falling)"
        },
        {
            "Symbol": "MANAPPURAM",
            "Price (\u20b9)": 351.75,
            "50 DMA": 320.65,
            "100 DMA": 297.74,
            "200 DMA": 293.91,
            "Dist from 200 DMA": "19.68%",
            "CAR Signal": "Short History"
        },
        {
            "Symbol": "LLOYDSENGG",
            "Price (\u20b9)": 91.17,
            "50 DMA": 79.47,
            "100 DMA": 64.64,
            "200 DMA": 59.49,
            "Dist from 200 DMA": "53.26%",
            "CAR Signal": "Short History"
        },
        {
            "Symbol": "DAVANGERE",
            "Price (\u20b9)": 3.39,
            "50 DMA": 3.7,
            "100 DMA": 3.75,
            "200 DMA": 3.89,
            "Dist from 200 DMA": "-12.75%",
            "CAR Signal": "AVOID (CAR Falling)"
        },
        {
            "Symbol": "WIPRO",
            "Price (\u20b9)": 174.97,
            "50 DMA": 185.11,
            "100 DMA": 191.81,
            "200 DMA": 216.47,
            "Dist from 200 DMA": "-19.17%",
            "CAR Signal": "AVOID (CAR Falling)"
        },
        {
            "Symbol": "UJJIVANSFB",
            "Price (\u20b9)": 65.63,
            "50 DMA": 57.61,
            "100 DMA": 57.13,
            "200 DMA": 56.31,
            "Dist from 200 DMA": "16.54%",
            "CAR Signal": "Short History"
        },
        {
            "Symbol": "VEDL",
            "Price (\u20b9)": 264.85,
            "50 DMA": 301.92,
            "100 DMA": 468.72,
            "200 DMA": 517.97,
            "Dist from 200 DMA": "-48.87%",
            "CAR Signal": "AVOID (CAR Falling)"
        },
        {
            "Symbol": "RPOWER",
            "Price (\u20b9)": 24.3,
            "50 DMA": 26.2,
            "100 DMA": 25.76,
            "200 DMA": 31.13,
            "Dist from 200 DMA": "-21.94%",
            "CAR Signal": "AVOID (CAR Falling)"
        },
        {
            "Symbol": "MOTHERSON",
            "Price (\u20b9)": 145.22,
            "50 DMA": 141.95,
            "100 DMA": 131.09,
            "200 DMA": 122.63,
            "Dist from 200 DMA": "18.42%",
            "CAR Signal": "AVOID (CAR Falling)"
        },
        {
            "Symbol": "RALLIS",
            "Price (\u20b9)": 228.62,
            "50 DMA": 235.12,
            "100 DMA": 243.14,
            "200 DMA": 254.14,
            "Dist from 200 DMA": "-10.04%",
            "CAR Signal": "AVOID (CAR Falling)"
        },
        {
            "Symbol": "SBIN",
            "Price (\u20b9)": 1044.4,
            "50 DMA": 1004.92,
            "100 DMA": 1032.23,
            "200 DMA": 1005.9,
            "Dist from 200 DMA": "3.83%",
            "CAR Signal": "BUY (CAR Rising)"
        },
        {
            "Symbol": "PAYTM",
            "Price (\u20b9)": 1300.5,
            "50 DMA": 1160.31,
            "100 DMA": 1122.83,
            "200 DMA": 1194.36,
            "Dist from 200 DMA": "8.89%",
            "CAR Signal": "Short History"
        },
        {
            "Symbol": "MAHABANK",
            "Price (\u20b9)": 81.75,
            "50 DMA": 83.04,
            "100 DMA": 76.88,
            "200 DMA": 68.12,
            "Dist from 200 DMA": "20.01%",
            "CAR Signal": "AVOID (CAR Falling)"
        },
        {
            "Symbol": "PPLPHARMA",
            "Price (\u20b9)": 184.81,
            "50 DMA": 170.98,
            "100 DMA": 161.73,
            "200 DMA": 170.33,
            "Dist from 200 DMA": "8.5%",
            "CAR Signal": "BUY (CAR Rising)"
        },
        {
            "Symbol": "ITC",
            "Price (\u20b9)": 281.0,
            "50 DMA": 287.92,
            "100 DMA": 292.3,
            "200 DMA": 325.96,
            "Dist from 200 DMA": "-13.79%",
            "CAR Signal": "AVOID (CAR Falling)"
        },
        {
            "Symbol": "IDBI",
            "Price (\u20b9)": 86.63,
            "50 DMA": 79.11,
            "100 DMA": 80.02,
            "200 DMA": 90.43,
            "Dist from 200 DMA": "-4.21%",
            "CAR Signal": "BUY (CAR Rising)"
        },
        {
            "Symbol": "DYCL",
            "Price (\u20b9)": 434.6,
            "50 DMA": 343.82,
            "100 DMA": 328.49,
            "200 DMA": 336.44,
            "Dist from 200 DMA": "29.17%",
            "CAR Signal": "BUY (CAR Rising)"
        },
        {
            "Symbol": "INFY",
            "Price (\u20b9)": 1073.5,
            "50 DMA": 1105.13,
            "100 DMA": 1167.07,
            "200 DMA": 1338.37,
            "Dist from 200 DMA": "-19.79%",
            "CAR Signal": "AVOID (CAR Falling)"
        },
        {
            "Symbol": "RAIN",
            "Price (\u20b9)": 223.4,
            "50 DMA": 188.85,
            "100 DMA": 157.36,
            "200 DMA": 145.03,
            "Dist from 200 DMA": "54.04%",
            "CAR Signal": "Short History"
        },
        {
            "Symbol": "SAIL",
            "Price (\u20b9)": 164.07,
            "50 DMA": 182.36,
            "100 DMA": 174.0,
            "200 DMA": 157.83,
            "Dist from 200 DMA": "3.96%",
            "CAR Signal": "AVOID (CAR Falling)"
        },
        {
            "Symbol": "J&KBANK",
            "Price (\u20b9)": 186.93,
            "50 DMA": 156.32,
            "100 DMA": 140.19,
            "200 DMA": 122.13,
            "Dist from 200 DMA": "53.06%",
            "CAR Signal": "Short History"
        },
        {
            "Symbol": "TFCILTD",
            "Price (\u20b9)": 83.21,
            "50 DMA": 76.46,
            "100 DMA": 73.24,
            "200 DMA": 70.79,
            "Dist from 200 DMA": "17.54%",
            "CAR Signal": "Short History"
        },
        {
            "Symbol": "NTPC",
            "Price (\u20b9)": 348.55,
            "50 DMA": 364.92,
            "100 DMA": 375.34,
            "200 DMA": 356.02,
            "Dist from 200 DMA": "-2.1%",
            "CAR Signal": "AVOID (CAR Falling)"
        },
        {
            "Symbol": "AWL",
            "Price (\u20b9)": 193.93,
            "50 DMA": 189.58,
            "100 DMA": 187.99,
            "200 DMA": 214.59,
            "Dist from 200 DMA": "-9.63%",
            "CAR Signal": "AVOID (CAR Falling)"
        },
        {
            "Symbol": "IFCI",
            "Price (\u20b9)": 72.87,
            "50 DMA": 74.03,
            "100 DMA": 65.46,
            "200 DMA": 60.26,
            "Dist from 200 DMA": "20.93%",
            "CAR Signal": "AVOID (CAR Falling)"
        },
        {
            "Symbol": "BHEL",
            "Price (\u20b9)": 413.3,
            "50 DMA": 400.93,
            "100 DMA": 348.65,
            "200 DMA": 307.24,
            "Dist from 200 DMA": "34.52%",
            "CAR Signal": "Short History"
        },
        {
            "Symbol": "CENTRALBK",
            "Price (\u20b9)": 32.02,
            "50 DMA": 32.11,
            "100 DMA": 33.66,
            "200 DMA": 35.32,
            "Dist from 200 DMA": "-9.35%",
            "CAR Signal": "AVOID (CAR Falling)"
        },
        {
            "Symbol": "SINDHUTRAD",
            "Price (\u20b9)": 25.2,
            "50 DMA": 25.41,
            "100 DMA": 24.5,
            "200 DMA": 23.72,
            "Dist from 200 DMA": "6.24%",
            "CAR Signal": "BUY (CAR Rising)"
        },
        {
            "Symbol": "RTNPOWER",
            "Price (\u20b9)": 8.85,
            "50 DMA": 9.22,
            "100 DMA": 9.06,
            "200 DMA": 9.41,
            "Dist from 200 DMA": "-5.95%",
            "CAR Signal": "AVOID (CAR Falling)"
        },
        {
            "Symbol": "ATALREAL",
            "Price (\u20b9)": 30.41,
            "50 DMA": 29.36,
            "100 DMA": 27.0,
            "200 DMA": 25.96,
            "Dist from 200 DMA": "17.16%",
            "CAR Signal": "BUY (CAR Rising)"
        },
        {
            "Symbol": "SHRIRAMFIN",
            "Price (\u20b9)": 1061.5,
            "50 DMA": 979.25,
            "100 DMA": 981.57,
            "200 DMA": 929.64,
            "Dist from 200 DMA": "14.18%",
            "CAR Signal": "BUY (CAR Rising)"
        },
        {
            "Symbol": "POWERGRID",
            "Price (\u20b9)": 286.7,
            "50 DMA": 289.12,
            "100 DMA": 297.3,
            "200 DMA": 284.42,
            "Dist from 200 DMA": "0.8%",
            "CAR Signal": "AVOID (CAR Falling)"
        },
        {
            "Symbol": "EXIDEIND",
            "Price (\u20b9)": 443.45,
            "50 DMA": 389.93,
            "100 DMA": 357.01,
            "200 DMA": 359.97,
            "Dist from 200 DMA": "23.19%",
            "CAR Signal": "Short History"
        },
        {
            "Symbol": "SBC",
            "Price (\u20b9)": 41.88,
            "50 DMA": 39.36,
            "100 DMA": 35.92,
            "200 DMA": 31.48,
            "Dist from 200 DMA": "33.03%",
            "CAR Signal": "AVOID (CAR Falling)"
        },
        {
            "Symbol": "ASHIANA",
            "Price (\u20b9)": 395.3,
            "50 DMA": 373.83,
            "100 DMA": 348.16,
            "200 DMA": 321.62,
            "Dist from 200 DMA": "22.91%",
            "CAR Signal": "AVOID (CAR Falling)"
        },
        {
            "Symbol": "LOTUSDEV",
            "Price (\u20b9)": 148.16,
            "50 DMA": 141.68,
            "100 DMA": 136.86,
            "200 DMA": 150.11,
            "Dist from 200 DMA": "-1.3%",
            "CAR Signal": "AVOID (CAR Falling)"
        },
        {
            "Symbol": "VMM",
            "Price (\u20b9)": 113.54,
            "50 DMA": 118.29,
            "100 DMA": 116.75,
            "200 DMA": 125.5,
            "Dist from 200 DMA": "-9.53%",
            "CAR Signal": "AVOID (CAR Falling)"
        },
        {
            "Symbol": "BAJFINANCE",
            "Price (\u20b9)": 1069.2,
            "50 DMA": 954.05,
            "100 DMA": 929.17,
            "200 DMA": 964.39,
            "Dist from 200 DMA": "10.87%",
            "CAR Signal": "BUY (CAR Rising)"
        },
        {
            "Symbol": "APOLLO",
            "Price (\u20b9)": 390.55,
            "50 DMA": 398.0,
            "100 DMA": 320.6,
            "200 DMA": 292.25,
            "Dist from 200 DMA": "33.64%",
            "CAR Signal": "AVOID (CAR Falling)"
        },
        {
            "Symbol": "LTF",
            "Price (\u20b9)": 306.75,
            "50 DMA": 291.49,
            "100 DMA": 281.92,
            "200 DMA": 284.89,
            "Dist from 200 DMA": "7.67%",
            "CAR Signal": "AVOID (CAR Falling)"
        },
        {
            "Symbol": "TARSONS",
            "Price (\u20b9)": 312.05,
            "50 DMA": 246.2,
            "100 DMA": 223.02,
            "200 DMA": 230.46,
            "Dist from 200 DMA": "35.4%",
            "CAR Signal": "BUY (CAR Rising)"
        },
        {
            "Symbol": "EASEMYTRIP",
            "Price (\u20b9)": 6.85,
            "50 DMA": 7.46,
            "100 DMA": 7.47,
            "200 DMA": 7.52,
            "Dist from 200 DMA": "-8.89%",
            "CAR Signal": "AVOID (CAR Falling)"
        },
        {
            "Symbol": "NBCC",
            "Price (\u20b9)": 96.8,
            "50 DMA": 101.39,
            "100 DMA": 95.18,
            "200 DMA": 102.31,
            "Dist from 200 DMA": "-5.38%",
            "CAR Signal": "AVOID (CAR Falling)"
        },
        {
            "Symbol": "FEDERALBNK",
            "Price (\u20b9)": 356.05,
            "50 DMA": 312.86,
            "100 DMA": 297.55,
            "200 DMA": 276.18,
            "Dist from 200 DMA": "28.92%",
            "CAR Signal": "Short History"
        },
        {
            "Symbol": "NELCAST",
            "Price (\u20b9)": 141.43,
            "50 DMA": 137.25,
            "100 DMA": 132.09,
            "200 DMA": 120.9,
            "Dist from 200 DMA": "16.98%",
            "CAR Signal": "BUY (CAR Rising)"
        },
        {
            "Symbol": "VIMTALABS",
            "Price (\u20b9)": 599.6,
            "50 DMA": 527.54,
            "100 DMA": 487.09,
            "200 DMA": 539.55,
            "Dist from 200 DMA": "11.13%",
            "CAR Signal": "BUY (CAR Rising)"
        },
        {
            "Symbol": "BPCL",
            "Price (\u20b9)": 319.35,
            "50 DMA": 303.06,
            "100 DMA": 306.94,
            "200 DMA": 329.39,
            "Dist from 200 DMA": "-3.05%",
            "CAR Signal": "AVOID (CAR Falling)"
        },
        {
            "Symbol": "SEPC",
            "Price (\u20b9)": 6.12,
            "50 DMA": 6.93,
            "100 DMA": 6.87,
            "200 DMA": 8.4,
            "Dist from 200 DMA": "-27.15%",
            "CAR Signal": "AVOID (CAR Falling)"
        },
        {
            "Symbol": "ACE",
            "Price (\u20b9)": 1035.5,
            "50 DMA": 942.28,
            "100 DMA": 905.29,
            "200 DMA": 934.55,
            "Dist from 200 DMA": "10.8%",
            "CAR Signal": "BUY (CAR Rising)"
        },
        {
            "Symbol": "KCPSUGIND",
            "Price (\u20b9)": 25.81,
            "50 DMA": 23.0,
            "100 DMA": 23.81,
            "200 DMA": 25.28,
            "Dist from 200 DMA": "2.1%",
            "CAR Signal": "AVOID (CAR Falling)"
        },
        {
            "Symbol": "TMPV",
            "Price (\u20b9)": 333.8,
            "50 DMA": 360.34,
            "100 DMA": 348.37,
            "200 DMA": 370.85,
            "Dist from 200 DMA": "-9.99%",
            "CAR Signal": "AVOID (CAR Falling)"
        },
        {
            "Symbol": "EXICOM",
            "Price (\u20b9)": 176.81,
            "50 DMA": 153.92,
            "100 DMA": 127.14,
            "200 DMA": 122.64,
            "Dist from 200 DMA": "44.17%",
            "CAR Signal": "AVOID (CAR Falling)"
        },
        {
            "Symbol": "MOREPENLAB",
            "Price (\u20b9)": 56.82,
            "50 DMA": 51.15,
            "100 DMA": 45.81,
            "200 DMA": 44.22,
            "Dist from 200 DMA": "28.51%",
            "CAR Signal": "AVOID (CAR Falling)"
        },
        {
            "Symbol": "PFC",
            "Price (\u20b9)": 414.85,
            "50 DMA": 425.15,
            "100 DMA": 427.19,
            "200 DMA": 399.44,
            "Dist from 200 DMA": "3.86%",
            "CAR Signal": "AVOID (CAR Falling)"
        },
        {
            "Symbol": "BAJAJHIND",
            "Price (\u20b9)": 17.35,
            "50 DMA": 18.31,
            "100 DMA": 17.98,
            "200 DMA": 18.57,
            "Dist from 200 DMA": "-6.56%",
            "CAR Signal": "AVOID (CAR Falling)"
        },
        {
            "Symbol": "AHCL",
            "Price (\u20b9)": 15.37,
            "50 DMA": 14.89,
            "100 DMA": 13.72,
            "200 DMA": 13.67,
            "Dist from 200 DMA": "12.42%",
            "CAR Signal": "BUY (CAR Rising)"
        },
        {
            "Symbol": "IRFC",
            "Price (\u20b9)": 88.31,
            "50 DMA": 94.63,
            "100 DMA": 97.13,
            "200 DMA": 107.64,
            "Dist from 200 DMA": "-17.96%",
            "CAR Signal": "AVOID (CAR Falling)"
        },
        {
            "Symbol": "VBL",
            "Price (\u20b9)": 463.45,
            "50 DMA": 509.66,
            "100 DMA": 479.26,
            "200 DMA": 473.34,
            "Dist from 200 DMA": "-2.09%",
            "CAR Signal": "AVOID (CAR Falling)"
        },
        {
            "Symbol": "ANGELONE",
            "Price (\u20b9)": 321.9,
            "50 DMA": 334.5,
            "100 DMA": 300.3,
            "200 DMA": 275.41,
            "Dist from 200 DMA": "16.88%",
            "CAR Signal": "AVOID (CAR Falling)"
        },
        {
            "Symbol": "UCOBANK",
            "Price (\u20b9)": 26.86,
            "50 DMA": 26.06,
            "100 DMA": 25.91,
            "200 DMA": 27.75,
            "Dist from 200 DMA": "-3.2%",
            "CAR Signal": "AVOID (CAR Falling)"
        },
        {
            "Symbol": "BEL",
            "Price (\u20b9)": 410.05,
            "50 DMA": 414.76,
            "100 DMA": 426.38,
            "200 DMA": 419.99,
            "Dist from 200 DMA": "-2.37%",
            "CAR Signal": "AVOID (CAR Falling)"
        },
        {
            "Symbol": "GATECH",
            "Price (\u20b9)": 0.48,
            "50 DMA": 0.51,
            "100 DMA": 0.49,
            "200 DMA": 0.53,
            "Dist from 200 DMA": "-9.95%",
            "CAR Signal": "AVOID (CAR Falling)"
        },
        {
            "Symbol": "IRB",
            "Price (\u20b9)": 19.96,
            "50 DMA": 20.95,
            "100 DMA": 21.04,
            "200 DMA": 21.09,
            "Dist from 200 DMA": "-5.34%",
            "CAR Signal": "AVOID (CAR Falling)"
        },
        {
            "Symbol": "INDUSINDBK",
            "Price (\u20b9)": 1063.45,
            "50 DMA": 939.8,
            "100 DMA": 901.49,
            "200 DMA": 876.32,
            "Dist from 200 DMA": "21.35%",
            "CAR Signal": "Short History"
        },
        {
            "Symbol": "BHARTIARTL",
            "Price (\u20b9)": 1948.4,
            "50 DMA": 1871.47,
            "100 DMA": 1855.41,
            "200 DMA": 1950.73,
            "Dist from 200 DMA": "-0.12%",
            "CAR Signal": "AVOID (CAR Falling)"
        },
        {
            "Symbol": "SWIGGY",
            "Price (\u20b9)": 270.23,
            "50 DMA": 255.58,
            "100 DMA": 268.56,
            "200 DMA": 324.57,
            "Dist from 200 DMA": "-16.74%",
            "CAR Signal": "AVOID (CAR Falling)"
        },
        {
            "Symbol": "HINDALCO",
            "Price (\u20b9)": 951.4,
            "50 DMA": 1022.65,
            "100 DMA": 995.32,
            "200 DMA": 925.96,
            "Dist from 200 DMA": "2.75%",
            "CAR Signal": "AVOID (CAR Falling)"
        },
        {
            "Symbol": "FINOPB",
            "Price (\u20b9)": 172.8,
            "50 DMA": 139.51,
            "100 DMA": 142.54,
            "200 DMA": 204.08,
            "Dist from 200 DMA": "-15.33%",
            "CAR Signal": "AVOID (CAR Falling)"
        },
        {
            "Symbol": "SHK",
            "Price (\u20b9)": 142.82,
            "50 DMA": 131.51,
            "100 DMA": 134.23,
            "200 DMA": 157.61,
            "Dist from 200 DMA": "-9.38%",
            "CAR Signal": "AVOID (CAR Falling)"
        },
        {
            "Symbol": "CUB",
            "Price (\u20b9)": 229.83,
            "50 DMA": 201.96,
            "100 DMA": 197.55,
            "200 DMA": 198.7,
            "Dist from 200 DMA": "15.67%",
            "CAR Signal": "Short History"
        },
        {
            "Symbol": "SAMMAANCAP",
            "Price (\u20b9)": 163.43,
            "50 DMA": 167.82,
            "100 DMA": 156.97,
            "200 DMA": 156.48,
            "Dist from 200 DMA": "4.44%",
            "CAR Signal": "BUY (CAR Rising)"
        },
        {
            "Symbol": "MOSCHIP",
            "Price (\u20b9)": 245.28,
            "50 DMA": 216.82,
            "100 DMA": 200.73,
            "200 DMA": 209.07,
            "Dist from 200 DMA": "17.32%",
            "CAR Signal": "BUY (CAR Rising)"
        },
        {
            "Symbol": "GAIL",
            "Price (\u20b9)": 173.99,
            "50 DMA": 169.42,
            "100 DMA": 162.25,
            "200 DMA": 165.16,
            "Dist from 200 DMA": "5.35%",
            "CAR Signal": "BUY (CAR Rising)"
        },
        {
            "Symbol": "HCLTECH",
            "Price (\u20b9)": 1239.5,
            "50 DMA": 1140.1,
            "100 DMA": 1219.19,
            "200 DMA": 1377.44,
            "Dist from 200 DMA": "-10.01%",
            "CAR Signal": "AVOID (CAR Falling)"
        },
        {
            "Symbol": "METAL",
            "Price (\u20b9)": 12.74,
            "50 DMA": 13.05,
            "100 DMA": 12.66,
            "200 DMA": 11.81,
            "Dist from 200 DMA": "7.83%",
            "CAR Signal": "AVOID (CAR Falling)"
        },
        {
            "Symbol": "COALINDIA",
            "Price (\u20b9)": 431.25,
            "50 DMA": 448.53,
            "100 DMA": 450.55,
            "200 DMA": 421.99,
            "Dist from 200 DMA": "2.2%",
            "CAR Signal": "AVOID (CAR Falling)"
        },
        {
            "Symbol": "ALOKINDS",
            "Price (\u20b9)": 12.31,
            "50 DMA": 12.71,
            "100 DMA": 13.08,
            "200 DMA": 14.71,
            "Dist from 200 DMA": "-16.31%",
            "CAR Signal": "AVOID (CAR Falling)"
        },
        {
            "Symbol": "NATIONALUM",
            "Price (\u20b9)": 342.9,
            "50 DMA": 377.53,
            "100 DMA": 387.48,
            "200 DMA": 338.19,
            "Dist from 200 DMA": "1.39%",
            "CAR Signal": "AVOID (CAR Falling)"
        },
        {
            "Symbol": "TARIL",
            "Price (\u20b9)": 316.85,
            "50 DMA": 325.28,
            "100 DMA": 312.3,
            "200 DMA": 319.15,
            "Dist from 200 DMA": "-0.72%",
            "CAR Signal": "AVOID (CAR Falling)"
        },
        {
            "Symbol": "RBLBANK",
            "Price (\u20b9)": 367.2,
            "50 DMA": 357.6,
            "100 DMA": 335.99,
            "200 DMA": 322.24,
            "Dist from 200 DMA": "13.95%",
            "CAR Signal": "Short History"
        },
        {
            "Symbol": "ORIENTHOT",
            "Price (\u20b9)": 146.54,
            "50 DMA": 117.68,
            "100 DMA": 106.57,
            "200 DMA": 110.06,
            "Dist from 200 DMA": "33.15%",
            "CAR Signal": "BUY (CAR Rising)"
        },
        {
            "Symbol": "CCAVENUE",
            "Price (\u20b9)": 17.04,
            "50 DMA": 15.23,
            "100 DMA": 14.93,
            "200 DMA": 16.32,
            "Dist from 200 DMA": "4.41%",
            "CAR Signal": "BUY (CAR Rising)"
        },
        {
            "Symbol": "UTKARSHBNK",
            "Price (\u20b9)": 14.91,
            "50 DMA": 13.92,
            "100 DMA": 13.55,
            "200 DMA": 14.77,
            "Dist from 200 DMA": "0.93%",
            "CAR Signal": "AVOID (CAR Falling)"
        },
        {
            "Symbol": "GREENPOWER",
            "Price (\u20b9)": 10.51,
            "50 DMA": 10.85,
            "100 DMA": 10.57,
            "200 DMA": 11.27,
            "Dist from 200 DMA": "-6.71%",
            "CAR Signal": "AVOID (CAR Falling)"
        },
        {
            "Symbol": "PATANJALI",
            "Price (\u20b9)": 340.25,
            "50 DMA": 422.42,
            "100 DMA": 448.02,
            "200 DMA": 500.47,
            "Dist from 200 DMA": "-32.01%",
            "CAR Signal": "AVOID (CAR Falling)"
        },
        {
            "Symbol": "LEMONTREE",
            "Price (\u20b9)": 110.95,
            "50 DMA": 113.9,
            "100 DMA": 113.23,
            "200 DMA": 132.36,
            "Dist from 200 DMA": "-16.18%",
            "CAR Signal": "AVOID (CAR Falling)"
        },
        {
            "Symbol": "HINDPETRO",
            "Price (\u20b9)": 406.95,
            "50 DMA": 391.98,
            "100 DMA": 381.91,
            "200 DMA": 419.76,
            "Dist from 200 DMA": "-3.05%",
            "CAR Signal": "AVOID (CAR Falling)"
        },
        {
            "Symbol": "RENUKA",
            "Price (\u20b9)": 22.23,
            "50 DMA": 22.92,
            "100 DMA": 24.7,
            "200 DMA": 25.76,
            "Dist from 200 DMA": "-13.71%",
            "CAR Signal": "AVOID (CAR Falling)"
        },
        {
            "Symbol": "NAUKRI",
            "Price (\u20b9)": 1207.7,
            "50 DMA": 1028.39,
            "100 DMA": 1011.81,
            "200 DMA": 1158.97,
            "Dist from 200 DMA": "4.2%",
            "CAR Signal": "AVOID (CAR Falling)"
        },
        {
            "Symbol": "HUHTAMAKI",
            "Price (\u20b9)": 264.19,
            "50 DMA": 188.89,
            "100 DMA": 180.44,
            "200 DMA": 196.4,
            "Dist from 200 DMA": "34.52%",
            "CAR Signal": "BUY (CAR Rising)"
        },
        {
            "Symbol": "ITCHOTELS",
            "Price (\u20b9)": 164.37,
            "50 DMA": 165.09,
            "100 DMA": 161.25,
            "200 DMA": 179.89,
            "Dist from 200 DMA": "-8.63%",
            "CAR Signal": "AVOID (CAR Falling)"
        },
        {
            "Symbol": "JSWCEMENT",
            "Price (\u20b9)": 140.97,
            "50 DMA": 131.06,
            "100 DMA": 126.29,
            "200 DMA": 124.77,
            "Dist from 200 DMA": "12.99%",
            "CAR Signal": "BUY (CAR Rising)"
        },
        {
            "Symbol": "DELHIVERY",
            "Price (\u20b9)": 484.75,
            "50 DMA": 470.39,
            "100 DMA": 456.82,
            "200 DMA": 442.39,
            "Dist from 200 DMA": "9.57%",
            "CAR Signal": "Short History"
        },
        {
            "Symbol": "MBAPL",
            "Price (\u20b9)": 143.75,
            "50 DMA": 115.2,
            "100 DMA": 107.63,
            "200 DMA": 95.74,
            "Dist from 200 DMA": "50.14%",
            "CAR Signal": "Short History"
        },
        {
            "Symbol": "KROSS",
            "Price (\u20b9)": 211.23,
            "50 DMA": 188.34,
            "100 DMA": 187.39,
            "200 DMA": 188.04,
            "Dist from 200 DMA": "12.33%",
            "CAR Signal": "BUY (CAR Rising)"
        },
        {
            "Symbol": "ATHERENERG",
            "Price (\u20b9)": 1288.4,
            "50 DMA": 1048.42,
            "100 DMA": 930.2,
            "200 DMA": 802.65,
            "Dist from 200 DMA": "60.52%",
            "CAR Signal": "Short History"
        },
        {
            "Symbol": "EDELWEISS",
            "Price (\u20b9)": 120.71,
            "50 DMA": 116.98,
            "100 DMA": 115.08,
            "200 DMA": 113.13,
            "Dist from 200 DMA": "6.7%",
            "CAR Signal": "AVOID (CAR Falling)"
        },
        {
            "Symbol": "ADANIENSOL",
            "Price (\u20b9)": 1741.6,
            "50 DMA": 1522.98,
            "100 DMA": 1331.74,
            "200 DMA": 1152.06,
            "Dist from 200 DMA": "51.17%",
            "CAR Signal": "Short History"
        },
        {
            "Symbol": "MSUMI",
            "Price (\u20b9)": 40.13,
            "50 DMA": 38.79,
            "100 DMA": 39.0,
            "200 DMA": 42.12,
            "Dist from 200 DMA": "-4.72%",
            "CAR Signal": "AVOID (CAR Falling)"
        },
        {
            "Symbol": "IGL",
            "Price (\u20b9)": 153.67,
            "50 DMA": 160.14,
            "100 DMA": 160.21,
            "200 DMA": 175.15,
            "Dist from 200 DMA": "-12.26%",
            "CAR Signal": "AVOID (CAR Falling)"
        },
        {
            "Symbol": "ANANTRAJ",
            "Price (\u20b9)": 608.85,
            "50 DMA": 535.19,
            "100 DMA": 511.52,
            "200 DMA": 547.06,
            "Dist from 200 DMA": "11.29%",
            "CAR Signal": "BUY (CAR Rising)"
        },
        {
            "Symbol": "BELRISE",
            "Price (\u20b9)": 236.76,
            "50 DMA": 227.04,
            "100 DMA": 213.49,
            "200 DMA": 189.78,
            "Dist from 200 DMA": "24.76%",
            "CAR Signal": "AVOID (CAR Falling)"
        },
        {
            "Symbol": "KPITTECH",
            "Price (\u20b9)": 564.45,
            "50 DMA": 691.62,
            "100 DMA": 702.57,
            "200 DMA": 917.01,
            "Dist from 200 DMA": "-38.45%",
            "CAR Signal": "AVOID (CAR Falling)"
        },
        {
            "Symbol": "CGPOWER",
            "Price (\u20b9)": 914.85,
            "50 DMA": 911.76,
            "100 DMA": 829.82,
            "200 DMA": 754.21,
            "Dist from 200 DMA": "21.3%",
            "CAR Signal": "AVOID (CAR Falling)"
        },
        {
            "Symbol": "SHALPAINTS",
            "Price (\u20b9)": 69.05,
            "50 DMA": 51.77,
            "100 DMA": 50.86,
            "200 DMA": 59.51,
            "Dist from 200 DMA": "16.03%",
            "CAR Signal": "AVOID (CAR Falling)"
        },
        {
            "Symbol": "TRIDENT",
            "Price (\u20b9)": 25.1,
            "50 DMA": 25.04,
            "100 DMA": 24.71,
            "200 DMA": 25.76,
            "Dist from 200 DMA": "-2.57%",
            "CAR Signal": "AVOID (CAR Falling)"
        },
        {
            "Symbol": "SHAH",
            "Price (\u20b9)": 4.35,
            "50 DMA": 4.79,
            "100 DMA": 4.91,
            "200 DMA": 4.72,
            "Dist from 200 DMA": "-7.76%",
            "CAR Signal": "AVOID (CAR Falling)"
        },
        {
            "Symbol": "FISCHER",
            "Price (\u20b9)": 39.98,
            "50 DMA": 36.5,
            "100 DMA": 37.17,
            "200 DMA": 47.91,
            "Dist from 200 DMA": "-16.55%",
            "CAR Signal": "AVOID (CAR Falling)"
        },
        {
            "Symbol": "RVNL",
            "Price (\u20b9)": 225.26,
            "50 DMA": 243.71,
            "100 DMA": 264.45,
            "200 DMA": 295.96,
            "Dist from 200 DMA": "-23.89%",
            "CAR Signal": "AVOID (CAR Falling)"
        },
        {
            "Symbol": "TIMETECHNO",
            "Price (\u20b9)": 207.86,
            "50 DMA": 179.14,
            "100 DMA": 178.59,
            "200 DMA": 187.69,
            "Dist from 200 DMA": "10.74%",
            "CAR Signal": "BUY (CAR Rising)"
        },
        {
            "Symbol": "RECLTD",
            "Price (\u20b9)": 362.05,
            "50 DMA": 349.96,
            "100 DMA": 347.8,
            "200 DMA": 351.43,
            "Dist from 200 DMA": "3.02%",
            "CAR Signal": "BUY (CAR Rising)"
        },
        {
            "Symbol": "RHETAN",
            "Price (\u20b9)": 28.26,
            "50 DMA": 28.47,
            "100 DMA": 27.16,
            "200 DMA": 25.67,
            "Dist from 200 DMA": "10.08%",
            "CAR Signal": "BUY (CAR Rising)"
        },
        {
            "Symbol": "NUVOCO",
            "Price (\u20b9)": 361.6,
            "50 DMA": 322.54,
            "100 DMA": 312.24,
            "200 DMA": 340.57,
            "Dist from 200 DMA": "6.18%",
            "CAR Signal": "AVOID (CAR Falling)"
        },
        {
            "Symbol": "LLOYDSENT",
            "Price (\u20b9)": 81.49,
            "50 DMA": 72.86,
            "100 DMA": 64.61,
            "200 DMA": 63.3,
            "Dist from 200 DMA": "28.73%",
            "CAR Signal": "BUY (CAR Rising)"
        },
        {
            "Symbol": "AEGISVOPAK",
            "Price (\u20b9)": 288.45,
            "50 DMA": 230.4,
            "100 DMA": 211.76,
            "200 DMA": 230.44,
            "Dist from 200 DMA": "25.17%",
            "CAR Signal": "Short History"
        },
        {
            "Symbol": "ABCAPITAL",
            "Price (\u20b9)": 409.05,
            "50 DMA": 374.66,
            "100 DMA": 353.52,
            "200 DMA": 346.07,
            "Dist from 200 DMA": "18.2%",
            "CAR Signal": "BUY (CAR Rising)"
        },
        {
            "Symbol": "JSWINFRA",
            "Price (\u20b9)": 344.55,
            "50 DMA": 301.09,
            "100 DMA": 281.56,
            "200 DMA": 279.08,
            "Dist from 200 DMA": "23.46%",
            "CAR Signal": "Short History"
        },
        {
            "Symbol": "BIOCON",
            "Price (\u20b9)": 440.3,
            "50 DMA": 421.4,
            "100 DMA": 395.81,
            "200 DMA": 387.68,
            "Dist from 200 DMA": "13.57%",
            "CAR Signal": "Short History"
        },
        {
            "Symbol": "ALLCARGO",
            "Price (\u20b9)": 8.17,
            "50 DMA": 8.55,
            "100 DMA": 8.56,
            "200 DMA": 12.85,
            "Dist from 200 DMA": "-36.41%",
            "CAR Signal": "AVOID (CAR Falling)"
        },
        {
            "Symbol": "SONACOMS",
            "Price (\u20b9)": 732.75,
            "50 DMA": 622.25,
            "100 DMA": 581.13,
            "200 DMA": 531.55,
            "Dist from 200 DMA": "37.85%",
            "CAR Signal": "Short History"
        },
        {
            "Symbol": "INOXWIND",
            "Price (\u20b9)": 79.02,
            "50 DMA": 88.33,
            "100 DMA": 89.34,
            "200 DMA": 108.61,
            "Dist from 200 DMA": "-27.24%",
            "CAR Signal": "AVOID (CAR Falling)"
        },
        {
            "Symbol": "PATELENG",
            "Price (\u20b9)": 29.78,
            "50 DMA": 29.5,
            "100 DMA": 28.0,
            "200 DMA": 30.03,
            "Dist from 200 DMA": "-0.84%",
            "CAR Signal": "AVOID (CAR Falling)"
        },
        {
            "Symbol": "GRANULES",
            "Price (\u20b9)": 875.7,
            "50 DMA": 798.15,
            "100 DMA": 718.41,
            "200 DMA": 644.91,
            "Dist from 200 DMA": "35.79%",
            "CAR Signal": "Short History"
        },
        {
            "Symbol": "NYKAA",
            "Price (\u20b9)": 327.95,
            "50 DMA": 290.71,
            "100 DMA": 273.38,
            "200 DMA": 265.52,
            "Dist from 200 DMA": "23.51%",
            "CAR Signal": "Short History"
        },
        {
            "Symbol": "LXCHEM",
            "Price (\u20b9)": 181.53,
            "50 DMA": 157.04,
            "100 DMA": 143.97,
            "200 DMA": 158.06,
            "Dist from 200 DMA": "14.85%",
            "CAR Signal": "BUY (CAR Rising)"
        },
        {
            "Symbol": "HINDZINC",
            "Price (\u20b9)": 534.4,
            "50 DMA": 573.72,
            "100 DMA": 570.57,
            "200 DMA": 558.81,
            "Dist from 200 DMA": "-4.37%",
            "CAR Signal": "AVOID (CAR Falling)"
        },
        {
            "Symbol": "IEX",
            "Price (\u20b9)": 124.43,
            "50 DMA": 123.51,
            "100 DMA": 123.2,
            "200 DMA": 128.37,
            "Dist from 200 DMA": "-3.07%",
            "CAR Signal": "AVOID (CAR Falling)"
        },
        {
            "Symbol": "JSFB",
            "Price (\u20b9)": 561.6,
            "50 DMA": 475.08,
            "100 DMA": 436.61,
            "200 DMA": 431.97,
            "Dist from 200 DMA": "30.01%",
            "CAR Signal": "Short History"
        },
        {
            "Symbol": "JYOTISTRUC",
            "Price (\u20b9)": 11.17,
            "50 DMA": 12.11,
            "100 DMA": 11.98,
            "200 DMA": 11.63,
            "Dist from 200 DMA": "-3.91%",
            "CAR Signal": "AVOID (CAR Falling)"
        },
        {
            "Symbol": "HINDCOPPER",
            "Price (\u20b9)": 492.45,
            "50 DMA": 520.03,
            "100 DMA": 525.71,
            "200 DMA": 483.16,
            "Dist from 200 DMA": "1.92%",
            "CAR Signal": "AVOID (CAR Falling)"
        },
        {
            "Symbol": "TATAPOWER",
            "Price (\u20b9)": 381.45,
            "50 DMA": 395.61,
            "100 DMA": 400.3,
            "200 DMA": 389.89,
            "Dist from 200 DMA": "-2.17%",
            "CAR Signal": "AVOID (CAR Falling)"
        },
        {
            "Symbol": "BALRAMCHIN",
            "Price (\u20b9)": 617.85,
            "50 DMA": 550.86,
            "100 DMA": 524.34,
            "200 DMA": 485.48,
            "Dist from 200 DMA": "27.27%",
            "CAR Signal": "Short History"
        },
        {
            "Symbol": "JMFINANCIL",
            "Price (\u20b9)": 124.04,
            "50 DMA": 125.61,
            "100 DMA": 126.61,
            "200 DMA": 135.88,
            "Dist from 200 DMA": "-8.71%",
            "CAR Signal": "AVOID (CAR Falling)"
        },
        {
            "Symbol": "GANDHAR",
            "Price (\u20b9)": 227.17,
            "50 DMA": 174.51,
            "100 DMA": 155.22,
            "200 DMA": 148.68,
            "Dist from 200 DMA": "52.79%",
            "CAR Signal": "Short History"
        },
        {
            "Symbol": "DLF",
            "Price (\u20b9)": 673.65,
            "50 DMA": 615.52,
            "100 DMA": 593.71,
            "200 DMA": 647.19,
            "Dist from 200 DMA": "4.09%",
            "CAR Signal": "AVOID (CAR Falling)"
        },
        {
            "Symbol": "TIRUPATIFL",
            "Price (\u20b9)": 76.95,
            "50 DMA": 52.59,
            "100 DMA": 47.59,
            "200 DMA": 41.83,
            "Dist from 200 DMA": "83.97%",
            "CAR Signal": "Short History"
        },
        {
            "Symbol": "SWSOLAR",
            "Price (\u20b9)": 207.31,
            "50 DMA": 217.03,
            "100 DMA": 202.87,
            "200 DMA": 209.76,
            "Dist from 200 DMA": "-1.17%",
            "CAR Signal": "AVOID (CAR Falling)"
        },
        {
            "Symbol": "JAMNAAUTO",
            "Price (\u20b9)": 136.07,
            "50 DMA": 126.72,
            "100 DMA": 125.79,
            "200 DMA": 121.15,
            "Dist from 200 DMA": "12.32%",
            "CAR Signal": "BUY (CAR Rising)"
        },
        {
            "Symbol": "E2E",
            "Price (\u20b9)": 446.4,
            "50 DMA": 391.22,
            "100 DMA": 325.16,
            "200 DMA": 289.47,
            "Dist from 200 DMA": "54.21%",
            "CAR Signal": "BUY (CAR Rising)"
        },
        {
            "Symbol": "EQUITASBNK",
            "Price (\u20b9)": 81.43,
            "50 DMA": 74.56,
            "100 DMA": 68.24,
            "200 DMA": 65.61,
            "Dist from 200 DMA": "24.12%",
            "CAR Signal": "Short History"
        },
        {
            "Symbol": "INDHOTEL",
            "Price (\u20b9)": 731.6,
            "50 DMA": 691.88,
            "100 DMA": 661.2,
            "200 DMA": 685.82,
            "Dist from 200 DMA": "6.67%",
            "CAR Signal": "BUY (CAR Rising)"
        },
        {
            "Symbol": "TINNARUBR",
            "Price (\u20b9)": 1148.9,
            "50 DMA": 883.85,
            "100 DMA": 782.76,
            "200 DMA": 802.67,
            "Dist from 200 DMA": "43.14%",
            "CAR Signal": "Short History"
        },
        {
            "Symbol": "IIFL",
            "Price (\u20b9)": 571.8,
            "50 DMA": 508.51,
            "100 DMA": 485.44,
            "200 DMA": 516.17,
            "Dist from 200 DMA": "10.78%",
            "CAR Signal": "BUY (CAR Rising)"
        },
        {
            "Symbol": "GABRIEL",
            "Price (\u20b9)": 1488.5,
            "50 DMA": 1170.99,
            "100 DMA": 1061.54,
            "200 DMA": 1064.6,
            "Dist from 200 DMA": "39.82%",
            "CAR Signal": "Short History"
        },
        {
            "Symbol": "TECHM",
            "Price (\u20b9)": 1576.3,
            "50 DMA": 1428.36,
            "100 DMA": 1402.11,
            "200 DMA": 1451.39,
            "Dist from 200 DMA": "8.61%",
            "CAR Signal": "BUY (CAR Rising)"
        },
        {
            "Symbol": "AGIIL",
            "Price (\u20b9)": 328.1,
            "50 DMA": 364.28,
            "100 DMA": 350.09,
            "200 DMA": 307.54,
            "Dist from 200 DMA": "6.69%",
            "CAR Signal": "AVOID (CAR Falling)"
        },
        {
            "Symbol": "IREDA",
            "Price (\u20b9)": 121.15,
            "50 DMA": 125.78,
            "100 DMA": 124.68,
            "200 DMA": 132.14,
            "Dist from 200 DMA": "-8.32%",
            "CAR Signal": "AVOID (CAR Falling)"
        },
        {
            "Symbol": "UPL",
            "Price (\u20b9)": 618.15,
            "50 DMA": 609.96,
            "100 DMA": 617.65,
            "200 DMA": 673.65,
            "Dist from 200 DMA": "-8.24%",
            "CAR Signal": "AVOID (CAR Falling)"
        },
        {
            "Symbol": "PETRONET",
            "Price (\u20b9)": 276.65,
            "50 DMA": 274.73,
            "100 DMA": 274.02,
            "200 DMA": 275.61,
            "Dist from 200 DMA": "0.38%",
            "CAR Signal": "BUY (CAR Rising)"
        },
        {
            "Symbol": "KTKBANK",
            "Price (\u20b9)": 281.3,
            "50 DMA": 267.34,
            "100 DMA": 251.86,
            "200 DMA": 221.82,
            "Dist from 200 DMA": "26.81%",
            "CAR Signal": "Short History"
        },
        {
            "Symbol": "SOBHA",
            "Price (\u20b9)": 1456.3,
            "50 DMA": 1401.4,
            "100 DMA": 1365.82,
            "200 DMA": 1435.02,
            "Dist from 200 DMA": "1.48%",
            "CAR Signal": "BUY (CAR Rising)"
        },
        {
            "Symbol": "ARVINDFASN",
            "Price (\u20b9)": 471.05,
            "50 DMA": 462.92,
            "100 DMA": 448.51,
            "200 DMA": 471.49,
            "Dist from 200 DMA": "-0.09%",
            "CAR Signal": "AVOID (CAR Falling)"
        },
        {
            "Symbol": "HDFCLIFE",
            "Price (\u20b9)": 561.0,
            "50 DMA": 580.98,
            "100 DMA": 601.08,
            "200 DMA": 672.77,
            "Dist from 200 DMA": "-16.61%",
            "CAR Signal": "AVOID (CAR Falling)"
        },
        {
            "Symbol": "COMSYN",
            "Price (\u20b9)": 188.48,
            "50 DMA": 168.41,
            "100 DMA": 161.66,
            "200 DMA": 157.47,
            "Dist from 200 DMA": "19.69%",
            "CAR Signal": "Short History"
        },
        {
            "Symbol": "RICOAUTO",
            "Price (\u20b9)": 137.58,
            "50 DMA": 129.0,
            "100 DMA": 121.71,
            "200 DMA": 116.66,
            "Dist from 200 DMA": "17.94%",
            "CAR Signal": "AVOID (CAR Falling)"
        },
        {
            "Symbol": "RAJRATAN",
            "Price (\u20b9)": 509.9,
            "50 DMA": 442.0,
            "100 DMA": 421.44,
            "200 DMA": 427.85,
            "Dist from 200 DMA": "19.18%",
            "CAR Signal": "BUY (CAR Rising)"
        },
        {
            "Symbol": "TBZ",
            "Price (\u20b9)": 259.73,
            "50 DMA": 183.58,
            "100 DMA": 161.39,
            "200 DMA": 166.55,
            "Dist from 200 DMA": "55.95%",
            "CAR Signal": "Short History"
        },
        {
            "Symbol": "ASHIMASYN",
            "Price (\u20b9)": 18.72,
            "50 DMA": 15.82,
            "100 DMA": 15.27,
            "200 DMA": 17.11,
            "Dist from 200 DMA": "9.42%",
            "CAR Signal": "AVOID (CAR Falling)"
        },
        {
            "Symbol": "NETWORK18",
            "Price (\u20b9)": 29.56,
            "50 DMA": 31.83,
            "100 DMA": 32.35,
            "200 DMA": 38.0,
            "Dist from 200 DMA": "-22.22%",
            "CAR Signal": "AVOID (CAR Falling)"
        },
        {
            "Symbol": "STEELXIND",
            "Price (\u20b9)": 11.96,
            "50 DMA": 11.92,
            "100 DMA": 10.34,
            "200 DMA": 9.61,
            "Dist from 200 DMA": "24.51%",
            "CAR Signal": "AVOID (CAR Falling)"
        },
        {
            "Symbol": "BCG",
            "Price (\u20b9)": 9.6,
            "50 DMA": 10.11,
            "100 DMA": 9.78,
            "200 DMA": 10.82,
            "Dist from 200 DMA": "-11.28%",
            "CAR Signal": "AVOID (CAR Falling)"
        },
        {
            "Symbol": "TVSMOTOR",
            "Price (\u20b9)": 3792.0,
            "50 DMA": 3476.53,
            "100 DMA": 3538.89,
            "200 DMA": 3578.9,
            "Dist from 200 DMA": "5.95%",
            "CAR Signal": "BUY (CAR Rising)"
        },
        {
            "Symbol": "TCS",
            "Price (\u20b9)": 2221.1,
            "50 DMA": 2173.8,
            "100 DMA": 2303.48,
            "200 DMA": 2644.89,
            "Dist from 200 DMA": "-16.02%",
            "CAR Signal": "AVOID (CAR Falling)"
        },
        {
            "Symbol": "LANDSMILL",
            "Price (\u20b9)": 0.76,
            "50 DMA": 0.85,
            "100 DMA": 0.93,
            "200 DMA": 1.16,
            "Dist from 200 DMA": "-34.36%",
            "CAR Signal": "AVOID (CAR Falling)"
        },
        {
            "Symbol": "AMBUJACEM",
            "Price (\u20b9)": 440.85,
            "50 DMA": 430.18,
            "100 DMA": 437.07,
            "200 DMA": 491.1,
            "Dist from 200 DMA": "-10.23%",
            "CAR Signal": "AVOID (CAR Falling)"
        },
        {
            "Symbol": "SIKKO",
            "Price (\u20b9)": 4.77,
            "50 DMA": 4.06,
            "100 DMA": 4.35,
            "200 DMA": 4.67,
            "Dist from 200 DMA": "2.07%",
            "CAR Signal": "AVOID (CAR Falling)"
        },
        {
            "Symbol": "RBA",
            "Price (\u20b9)": 65.88,
            "50 DMA": 71.1,
            "100 DMA": 66.99,
            "200 DMA": 66.56,
            "Dist from 200 DMA": "-1.02%",
            "CAR Signal": "AVOID (CAR Falling)"
        },
        {
            "Symbol": "NAZARA",
            "Price (\u20b9)": 309.3,
            "50 DMA": 292.63,
            "100 DMA": 272.91,
            "200 DMA": 268.35,
            "Dist from 200 DMA": "15.26%",
            "CAR Signal": "BUY (CAR Rising)"
        },
        {
            "Symbol": "RKFORGE",
            "Price (\u20b9)": 576.3,
            "50 DMA": 568.78,
            "100 DMA": 558.52,
            "200 DMA": 545.29,
            "Dist from 200 DMA": "5.69%",
            "CAR Signal": "BUY (CAR Rising)"
        },
        {
            "Symbol": "IOLCP",
            "Price (\u20b9)": 151.0,
            "50 DMA": 136.71,
            "100 DMA": 109.52,
            "200 DMA": 96.81,
            "Dist from 200 DMA": "55.97%",
            "CAR Signal": "Short History"
        },
        {
            "Symbol": "HARDWYN",
            "Price (\u20b9)": 15.73,
            "50 DMA": 23.71,
            "100 DMA": 22.44,
            "200 DMA": 19.28,
            "Dist from 200 DMA": "-18.43%",
            "CAR Signal": "AVOID (CAR Falling)"
        },
        {
            "Symbol": "SOUTHWEST",
            "Price (\u20b9)": 249.09,
            "50 DMA": 241.37,
            "100 DMA": 228.93,
            "200 DMA": 204.36,
            "Dist from 200 DMA": "21.89%",
            "CAR Signal": "AVOID (CAR Falling)"
        },
        {
            "Symbol": "RESPONIND",
            "Price (\u20b9)": 181.84,
            "50 DMA": 185.97,
            "100 DMA": 170.84,
            "200 DMA": 181.35,
            "Dist from 200 DMA": "0.27%",
            "CAR Signal": "AVOID (CAR Falling)"
        },
        {
            "Symbol": "DRREDDY",
            "Price (\u20b9)": 1206.0,
            "50 DMA": 1289.07,
            "100 DMA": 1278.75,
            "200 DMA": 1258.63,
            "Dist from 200 DMA": "-4.18%",
            "CAR Signal": "AVOID (CAR Falling)"
        }
    ]
}